{
  "description": "Spot-size divergence constraints: theta <= r/L where r=hole radius, L=distance",
  "formula": "theta_max = holeRadius_m / distance_m",
  "holeRadius_m": 0.005,
  "constraints": [
    { "distance_m": 10,    "distance_label": "10 m",  "maxDivergence_rad": 5e-4 },
    { "distance_m": 100,   "distance_label": "100 m", "maxDivergence_rad": 5e-5 },
    { "distance_m": 1000,  "distance_label": "1 km",  "maxDivergence_rad": 5e-6 },
    { "distance_m": 10000, "distance_label": "10 km",  "maxDivergence_rad": 5e-7 }
  ],
  "note": "Once beam divergence exceeds this, no finite increase in power can compensate — beam no longer concentrates energy into the hole"
}
